{
  "experiment": {
    "name": "boussinesq_affine_d8",
    "problem": "boussinesq",
    "coefficient": "affine",
    "dimension": 8,
    "targets": [
      "u",
      "phi",
      "p"
    ],
    "paper_reference": "appendix_b_boussinesq",
    "implementation_note": "Simplified 2D finite-difference Boussinesq-style solver; paper uses a 3D mixed FEM formulation."
  },
  "grid": {
    "shape": [
      8,
      8
    ]
  },
  "pde": {
    "equation": "stationary_boussinesq",
    "pressure_normalization": "zero_mean",
    "physical_parameters": {
      "gravity": {
        "gx": 0.0,
        "gy": 0.0,
        "gz": -1.0
      },
      "viscosity_temperature_law": {
        "formula": "0.1 + exp(-phi)"
      },
      "thermal_conductivity": {
        "base_value": 1.89,
        "decay_power": 1.8,
        "coordinate": "z3",
        "diagonal_scaling": [
          "exp(-z1)",
          "exp(-z2)",
          "exp(-z3)"
        ],
        "formula": "(1.89 + sum_j x_j sin(pi z_3 j) / j^(9/5)) * diag(exp(-z1), exp(-z2), exp(-z3))"
      }
    },
    "boundary_conditions": {
      "type": "paper_like",
      "velocity": {
        "bottom": {
          "value": [
            1.0,
            1.0,
            0.0
          ]
        },
        "elsewhere": {
          "value": [
            0.0,
            0.0,
            0.0
          ]
        }
      },
      "temperature": {
        "bottom": {
          "formula": "exp(4*(-(z1 - 0.5)^2 - (z2 - 0.5)^2))"
        },
        "elsewhere": {
          "value": 0.0
        }
      }
    }
  },
  "coefficient": {
    "name": "affine",
    "base_value": 2.62,
    "decay_power": 1.5,
    "spatial_coordinate": "z1",
    "basis": "sine",
    "formula": "2.62 + sum_{j=1}^d x_j sin(pi z_1 j) / j^(3/2)",
    "parameter_domain": [
      -1.0,
      1.0
    ]
  },
  "data": {
    "train_sizes": [
      10,
      20,
      30,
      40,
      50,
      60,
      70,
      80,
      90,
      100,
      200,
      300,
      400,
      500
    ],
    "paper_train_sizes": [
      10,
      20,
      30,
      40,
      50,
      60,
      70,
      80,
      90,
      100,
      200,
      300,
      400,
      500
    ],
    "test_size": 500,
    "seeds": [
      0,
      1,
      2
    ],
    "dtype": "float32"
  },
  "output": {
    "output_dimensions": {
      "y_u": 128,
      "y_phi": 64,
      "y_p": 64
    }
  },
  "note": "Simplified finite-difference Boussinesq-style dataset. This is not the exact mixed FEM Boussinesq solver from the target paper. If the config specifies a 3D unit cube, this implementation uses a 2D slice with nx by ny grid points."
}